augaudio/__init__.py
augaudio/cli.py
augmentaudio-1.0.6.dist-info/LICENSE
augmentaudio-1.0.6.dist-info/METADATA
augmentaudio-1.0.6.dist-info/WHEEL
augmentaudio-1.0.6.dist-info/entry_points.txt
augmentaudio-1.0.6.dist-info/top_level.txt
augmentaudio-1.0.6.dist-info/RECORD
